rowordnet/__init__.py
rowordnet/demo.py
rowordnet/exceptions.py
rowordnet/rowordnet.pickle
rowordnet/rowordnet.py
rowordnet/synset.py
tests/__init__.py
tests/unit-tests.py
rowordnet-1.1.0.dist-info/LICENSE
rowordnet-1.1.0.dist-info/METADATA
rowordnet-1.1.0.dist-info/WHEEL
rowordnet-1.1.0.dist-info/top_level.txt
rowordnet-1.1.0.dist-info/RECORD
