Metadata-Version: 2.1
Name: rowordnet
Version: 1.1.0
Summary: Python API for the Romanian WordNet
Home-page: https://github.com/dumitrescustefan/RoWordNet
Author: Stefan Daniel Dumitrescu and Andrei Marius Avram
Author-email: dumitrescu.stefan@gmail.com, avram.andreimarius@gmail.com
Maintainer: Stefan Daniel Dumitrescu and Andrei Marius Avram
Maintainer-email: dumitrescu.stefan@gmail.com, avram.andreimarius@gmail.com
License: UNKNOWN
Keywords: romanian wordnet rowordnet rown python
Platform: UNKNOWN
Classifier: Development Status :: 5 - Production/Stable
Classifier: Intended Audience :: Developers
Classifier: Intended Audience :: Education
Classifier: Intended Audience :: Information Technology
Classifier: Intended Audience :: Science/Research
Classifier: Topic :: Scientific/Engineering
Classifier: Topic :: Scientific/Engineering :: Human Machine Interfaces
Classifier: Topic :: Scientific/Engineering :: Information Analysis
Classifier: Topic :: Text Processing
Classifier: Topic :: Text Processing :: Filters
Classifier: Topic :: Text Processing :: General
Classifier: Topic :: Text Processing :: Indexing
Classifier: Topic :: Text Processing :: Linguistic
Classifier: License :: OSI Approved :: GNU General Public License v3 (GPLv3)
Classifier: Programming Language :: Python :: 3
Requires-Dist: networkx
Requires-Dist: lxml
